ggml_ot/__init__.py
ggml_ot/benchmark/__init__.py
ggml_ot/benchmark/classify.py
ggml_ot/benchmark/cluster.py
ggml_ot/benchmark/hyperparams.py
ggml_ot/benchmark/pivoted_chol.py
ggml_ot/benchmark/test.py
ggml_ot/data/__init__.py
ggml_ot/data/anndata.py
ggml_ot/data/generic.py
ggml_ot/data/synthetic.py
ggml_ot/data/util.py
ggml_ot/distances/__init__.py
ggml_ot/distances/dists.py
ggml_ot/distances/gaussian_emd.py
ggml_ot/distances/mahalanobis.py
ggml_ot/distances/utils.py
ggml_ot/experimental/__init__.py
ggml_ot/experimental/margins.py
ggml_ot/gene/__init__.py
ggml_ot/gene/_enrichment.py
ggml_ot/gene/interpret_subspace.py
ggml_ot/gene/ranking.py
ggml_ot/ggml.py
ggml_ot/interface.py
ggml_ot/optimization/__init__.py
ggml_ot/optimization/regularization.py
ggml_ot/plot/__init__.py
ggml_ot/plot/clustermap.py
ggml_ot/plot/contour.py
ggml_ot/plot/embedding.py
ggml_ot/plot/eval.py
ggml_ot/plot/plotting.py
ggml_ot/settings.py
ggml_ot-0.9.9.dist-info/METADATA
ggml_ot-0.9.9.dist-info/WHEEL
ggml_ot-0.9.9.dist-info/licenses/LICENSE
ggml_ot-0.9.9.dist-info/RECORD
