Metadata-Version: 2.4
Name: ggml-ot
Version: 0.9.9
Summary: Supervised OT with Global Ground Metric Learning
License-File: LICENSE
Author: Damin Kuehn
Author-email: kuehn@cs.rwth-aachen.de
Requires-Python: >=3.11
Classifier: Programming Language :: Python :: 3
Classifier: Development Status :: 5 - Production/Stable
Classifier: Framework :: Sphinx
Classifier: Intended Audience :: Science/Research
Classifier: Intended Audience :: Healthcare Industry
Classifier: Topic :: Scientific/Engineering :: Bio-Informatics
Classifier: Topic :: Scientific/Engineering :: Information Analysis
Classifier: Topic :: Scientific/Engineering :: Medical Science Apps.
Requires-Dist: anndata (>=0.11.4,<0.12.0)
Requires-Dist: gprofiler-official (>=1.0.0,<2.0.0)
Requires-Dist: igraph (>=0.11.9,<0.12.0)
Requires-Dist: ipython (>=9.3.0,<10.0.0)
Requires-Dist: matplotlib (>=3.10.1,<4.0.0)
Requires-Dist: numpy (>=2.2.4,<3.0.0)
Requires-Dist: pandas (>=2.2.3,<3.0.0)
Requires-Dist: pot (>=0.9.5,<0.10.0)
Requires-Dist: pydiffmap (>=0.2.0.1,<0.3.0.0)
Requires-Dist: requests (>=2.32.4,<3.0.0)
Requires-Dist: scanpy (>=1.11.1,<2.0.0)
Requires-Dist: scikit-learn (>=1.7.2,<1.8)
Requires-Dist: scipy (>=1.15.2,<2.0.0)
Requires-Dist: seaborn (>=0.13.2,<0.14.0)
Requires-Dist: torch (>=2.6.0,<3.0.0)
Requires-Dist: tqdm (>=4.67.1,<5.0.0)
Requires-Dist: umap-learn (>=0.5.7,<0.6.0)
Project-URL: Homepage, https://github.com/DaminK/ggml-ot
Project-URL: Issues, https://github.com/DaminK/ggml-ot/issues
